cdm_cli/__init__.py
cdm_cli/chapter.py
cdm_cli/cli.py
cdm_cli/exeptions.py
cdm_cli/finder.py
cdm_cli/manga.py
cdm_cli/page.py
cdm_cli-0.1.2.dist-info/entry_points.txt
cdm_cli-0.1.2.dist-info/LICENSE
cdm_cli-0.1.2.dist-info/WHEEL
cdm_cli-0.1.2.dist-info/METADATA
cdm_cli-0.1.2.dist-info/RECORD
